{
  "permissions": {
    "Bash(mkfs*)": "deny",
    "Bash(dd if=* of=/dev/*)": "deny",
    "Bash(curl * | bash)": "deny",
    "Bash(curl * | sh)": "deny",
    "Bash(wget * | bash)": "deny",
    "Bash(wget * | sh)": "deny",
    "Bash(bash -i >* /dev/tcp/*)": "deny",

    "Bash(rm -rf *)": "ask",
    "Bash(rm -r *)": "ask",
    "Bash(rmdir *)": "ask",
    "Bash(sudo *)": "ask",
    "Bash(chmod 777 *)": "ask",
    "Bash(chmod -R 777 *)": "ask",
    "Bash(chown root *)": "ask",
    "Bash(chown -R root *)": "ask",
    "Bash(git push --force*)": "ask",
    "Bash(git push -f *)": "ask",
    "Bash(git push *--force*)": "ask",
    "Bash(git reset --hard*)": "ask",
    "Bash(git clean -fd*)": "ask",
    "Bash(git branch -D *)": "ask",
    "Bash(git filter-branch*)": "ask",
    "Bash(git push --delete*)": "ask",
    "Bash(git push --mirror*)": "ask",
    "Bash(curl * -d *)": "ask",
    "Bash(curl * --data*)": "ask",
    "Bash(curl * -F *)": "ask",
    "Bash(curl * --upload*)": "ask",
    "Bash(curl * -T *)": "ask",
    "Bash(scp * *@*)": "ask",
    "Bash(rsync * *@*)": "ask",
    "Bash(nc -e*)": "ask",
    "Bash(printenv*)": "ask",
    "Bash(cat *.env)": "ask",
    "Bash(cat *.env.*)": "ask",
    "Bash(cat *.pem)": "ask",
    "Bash(cat *.key)": "ask",
    "Bash(pip install *--index-url*)": "ask",
    "Bash(pip install *--extra-index*)": "ask",
    "Bash(npm install *--registry*)": "ask",
    "Bash(kill -9 *)": "ask",
    "Bash(killall *)": "ask",
    "Bash(pkill *)": "ask",
    "Bash(systemctl stop *)": "ask",
    "Bash(systemctl disable *)": "ask",
    "Bash(crontab -r*)": "ask",
    "Bash(*DROP TABLE*)": "ask",
    "Bash(*DROP DATABASE*)": "ask",
    "Bash(*TRUNCATE TABLE*)": "ask",

    "Write(*.env)": "ask",
    "Write(*.env.*)": "ask",
    "Write(*.pem)": "ask",
    "Write(*.key)": "ask",
    "Write(*.p12)": "ask",
    "Write(*credentials*)": "ask",
    "Write(*.secret)": "ask",
    "Edit(*.env)": "ask",
    "Edit(*.env.*)": "ask",
    "Edit(*.pem)": "ask",
    "Edit(*.key)": "ask",
    "Edit(*.p12)": "ask",
    "Edit(*credentials*)": "ask",
    "Edit(*.secret)": "ask"
  }
}
